flake8_flask_openapi_docstring/__init__.py
flake8_flask_openapi_docstring/__version__.py
flake8_flask_openapi_docstring/linter.py
flake8_flask_openapi_docstring/types.py
flake8_flask_openapi_docstring/visitor.py
flake8_flask_openapi_docstring-0.1.2.dist-info/WHEEL
flake8_flask_openapi_docstring-0.1.2.dist-info/LICENSE
flake8_flask_openapi_docstring-0.1.2.dist-info/METADATA
flake8_flask_openapi_docstring-0.1.2.dist-info/entry_points.txt
flake8_flask_openapi_docstring-0.1.2.dist-info/RECORD
