Metadata-Version: 2.1
Name: flake8-flask-openapi-docstring
Version: 0.1.2
Summary: A Flake8 plugin to enforce OpenAPI docstrings in Flask routes
Home-page: https://github.com/expobrain/flake8-flask-openapi-docstring
License: MIT
Author: Daniele Esposti
Author-email: daniele.esposti@gmail.com
Requires-Python: >=3.7,<3.12
Classifier: License :: OSI Approved :: MIT License
Classifier: Programming Language :: Python :: 3
Classifier: Programming Language :: Python :: 3.7
Classifier: Programming Language :: Python :: 3.8
Classifier: Programming Language :: Python :: 3.9
Classifier: Programming Language :: Python :: 3.10
Classifier: Programming Language :: Python :: 3.11
Requires-Dist: apispec (>3)
Requires-Dist: pyyaml (>=5.4)
Project-URL: Repository, https://github.com/expobrain/flake8-flask-openapi-docstring
